bwpy/__init__.py
bwpy/_channels.py
bwpy/_hdf_annotations.py
bwpy/decoders.py
bwpy/exceptions.py
bwpy/readers.py
bwpy/writers.py
brainwavepy-1.0.0b0.dist-info/LICENSE
brainwavepy-1.0.0b0.dist-info/METADATA
brainwavepy-1.0.0b0.dist-info/WHEEL
brainwavepy-1.0.0b0.dist-info/top_level.txt
brainwavepy-1.0.0b0.dist-info/RECORD
